{
    "Config": [
        { "CassetteNumber":  0, "Ring": 2, "FEN": 0, "Thresholds": [[0],[0]], "Hybrid": 3, "HybridId": "a08000ea3c80a0803410082006704410" },
        { "CassetteNumber":  1, "Ring": 2, "FEN": 0, "Thresholds": [[0],[0]], "Hybrid": 2, "HybridId": "00000000000000000000000000000000" },
        { "CassetteNumber":  2, "Ring": 2, "FEN": 0, "Thresholds": [[0],[0]], "Hybrid": 1, "HybridId": "a080005ab460a0803410082006704410" },
        { "CassetteNumber":  3, "Ring": 2, "FEN": 0, "Thresholds": [[0],[0]], "Hybrid": 0, "HybridId": "a080005d489ba0803410082006704410" },
        { "CassetteNumber":  4, "Ring": 1, "FEN": 0, "Thresholds": [[0],[0]], "Hybrid": 4, "HybridId": "a08000bb207ca0803410082006704410" },
        { "CassetteNumber":  5, "Ring": 1, "FEN": 0, "Thresholds": [[0],[0]], "Hybrid": 3, "HybridId": "a080005d248da0803410082106704410" },
        { "CassetteNumber":  6, "Ring": 1, "FEN": 0, "Thresholds": [[0],[0]], "Hybrid": 2, "HybridId": "a08000ad0cc6a0803410082106704410" },
        { "CassetteNumber":  7, "Ring": 1, "FEN": 0, "Thresholds": [[0],[0]], "Hybrid": 1, "HybridId": "a08000275c9da0803410082106704410" },
        { "CassetteNumber":  8, "Ring": 1, "FEN": 0, "Thresholds": [[0],[0]], "Hybrid": 0, "HybridId": "a0800006b882a0803410082006704410" },
        { "CassetteNumber":  9, "Ring": 0, "FEN": 0, "Thresholds": [[0],[0]], "Hybrid": 4, "HybridId": "a08000e82859a0803410082006704410" },
        { "CassetteNumber": 10, "Ring": 0, "FEN": 0, "Thresholds": [[0],[0]], "Hybrid": 3, "HybridId": "a0800096b8b2a0803410082006704410" },
        { "CassetteNumber": 11, "Ring": 0, "FEN": 0, "Thresholds": [[0],[0]], "Hybrid": 2, "HybridId": "a0800099b869a0803410082006704410" },
        { "CassetteNumber": 12, "Ring": 0, "FEN": 0, "Thresholds": [[0],[0]], "Hybrid": 1, "HybridId": "a0800017b4cca0803410082006704410" },
        { "CassetteNumber": 13, "Ring": 0, "FEN": 0, "Thresholds": [[0],[0]], "Hybrid": 0, "HybridId": "a08000962073a0803410082006704410" }
    ],

    "Date": "2025-04-14 14:13:48",
    "History": [
        "2023-09-12 Change hybrid order",
        "2023-09-25 Added hybrid id's",
        "2023-10-06 add info fields to config file, thresholds"
    ],

    "Comment"            : "layout for AMOR for the PSI visit 2023-10",
    "Info"               : "Generated by vmmdcs version 20231103",
    "Detector"           : "Freia",
    "InstrumentGeometry" : "AMOR",
    "MaxGapStrip"        : 1,
    "MaxGapWire"         : 1,
    "MaxPulseTimeNS"     : 2071428570,
    "Version"            : 1,
    "VersionStr"         : "v1: strip and wire thresholds per cassette, not per channel",
    "WireChOffset"       : 16
}
